tivatci/__init__.py
tivatci/__main__.py
tivatci-0.5.8.dist-info/licenses/LICENSE
tivatci-0.5.8.dist-info/METADATA
tivatci-0.5.8.dist-info/WHEEL
tivatci-0.5.8.dist-info/top_level.txt
tivatci-0.5.8.dist-info/RECORD
