Metadata-Version: 2.4
Name: tivatci
Version: 0.5.8
Summary: Python TIVA/TCI Library
Author-email: Hyung-Chul Lee <vital@snu.ac.kr>
License-Expression: MIT
Requires-Python: >=3.0
License-File: LICENSE
Requires-Dist: numpy
Requires-Dist: pandas
Requires-Dist: matplotlib
Requires-Dist: scipy
Dynamic: license-file
